Metadata-Version: 1.1
Name: hqscord
Version: 1.0.0
Summary: For hqs.bot to create cogs (faster)
Home-page: https://github.com/philliphqs/hqscord
Author: philliphqs
Author-email: UNKNOWN
License: MIT
Download-URL: https://github.com/philliphqs/hqscord/archive/1.0.0.tar.gz
Keywords: hqs,philliphqs,hqs.bot,hqsartworks,hqsartworks.me,discord,discord.py
Platform: UNKNOWN
Classifier: Intended Audience :: Developers
Classifier: Topic :: Software Development :: Build Tools
Classifier: License :: OSI Approved :: MIT License
Classifier: Programming Language :: Python :: 3
Classifier: Programming Language :: Python :: 3.4
Classifier: Programming Language :: Python :: 3.5
Classifier: Programming Language :: Python :: 3.6
Classifier: Programming Language :: Python :: 3.7
Classifier: Programming Language :: Python :: 3.8
